fscraper/__init__.py
fscraper/constant_table.py
fscraper/exceptions.py
fscraper/kabutanscraper.py
fscraper/kabuyohoscraper.py
fscraper/minkabuscraper.py
fscraper/reuterscraper.py
fscraper/utils.py
fscraper/yfscraper.py
fscraper-1.0.9.dist-info/LICENSE
fscraper-1.0.9.dist-info/METADATA
fscraper-1.0.9.dist-info/WHEEL
fscraper-1.0.9.dist-info/top_level.txt
fscraper-1.0.9.dist-info/RECORD
