Metadata-Version: 2.1
Name: fscraper
Version: 1.0.9
Summary: Financial Data Web Scraper
Home-page: https://github.com/er-ri/fscraper
Author: er-ri
Author-email: 724chen@gmail.com
Classifier: Programming Language :: Python :: 3.10
Classifier: License :: OSI Approved :: MIT License
Requires-Python: >=3.8
License-File: LICENSE
Requires-Dist: pandas >=1.5.2
Requires-Dist: numpy >=1.23.5
Requires-Dist: requests >=2.28.1
Requires-Dist: beautifulsoup4 >=4.12.2
Requires-Dist: lxml >=4.9.2
